<annotation><filename>c8b2aaa6-1a53d715.jpg</filename><attributes><weather>rainy</weather><scene>residential</scene><timeofday>daytime</timeofday></attributes><object><name>car</name><bndbox><xmin>633</xmin><ymin>244</ymin><xmax>650</xmax><ymax>264</ymax></bndbox><difficult>0</difficult><truncated>0</truncated><pose>0</pose></object><object><name>car</name><bndbox><xmin>618</xmin><ymin>243</ymin><xmax>639</xmax><ymax>267</ymax></bndbox><difficult>0</difficult><truncated>0</truncated><pose>0</pose></object><object><name>car</name><bndbox><xmin>587</xmin><ymin>238</ymin><xmax>626</xmax><ymax>273</ymax></bndbox><difficult>0</difficult><truncated>0</truncated><pose>0</pose></object><object><name>car</name><bndbox><xmin>532</xmin><ymin>237</ymin><xmax>601</xmax><ymax>287</ymax></bndbox><difficult>0</difficult><truncated>0</truncated><pose>0</pose></object><object><name>car</name><bndbox><xmin>508</xmin><ymin>244</ymin><xmax>578</xmax><ymax>295</ymax></bndbox><difficult>0</difficult><truncated>0</truncated><pose>0</pose></object><object><name>car</name><bndbox><xmin>436</xmin><ymin>246</ymin><xmax>538</xmax><ymax>315</ymax></bndbox><difficult>0</difficult><truncated>0</truncated><pose>0</pose></object><object><name>car</name><bndbox><xmin>214</xmin><ymin>252</ymin><xmax>431</xmax><ymax>389</ymax></bndbox><difficult>0</difficult><truncated>0</truncated><pose>0</pose></object><object><name>car</name><bndbox><xmin>0</xmin><ymin>268</ymin><xmax>217</xmax><ymax>468</ymax></bndbox><difficult>0</difficult><truncated>0</truncated><pose>0</pose></object></annotation>